rc_fpv/__init__.py
rc_fpv/rc-fpv.py
rc_fpv-0.0.6.dist-info/METADATA
rc_fpv-0.0.6.dist-info/WHEEL
rc_fpv-0.0.6.dist-info/top_level.txt
rc_fpv-0.0.6.dist-info/RECORD
